ahs/__init__.py
ahs/__main__.py
ahs/editor_loadtime.py
ahs/sanitize_har.py
ahs/to_timing_csv.py
annofab_har-0.1.2.dist-info/METADATA
annofab_har-0.1.2.dist-info/WHEEL
annofab_har-0.1.2.dist-info/entry_points.txt
annofab_har-0.1.2.dist-info/RECORD
