Metadata-Version: 2.4
Name: annofab-har
Version: 0.1.2
Project-URL: Repository, https://github.com/kurusugawa-computer/annofab-har
Author: Kurusugawa Computer Inc.
License-Expression: MIT
Classifier: Development Status :: 4 - Beta
Classifier: Environment :: Console
Classifier: Intended Audience :: Developers
Classifier: Operating System :: OS Independent
Classifier: Programming Language :: Python :: 3.10
Classifier: Programming Language :: Python :: 3.11
Classifier: Programming Language :: Python :: 3.12
Classifier: Programming Language :: Python :: 3.13
Classifier: Topic :: Utilities
Requires-Python: >=3.10
Requires-Dist: pandas
